packagelister/__init__.py
packagelister/localscanner.py
packagelister/packagelister.py
packagelister/packagelister_cli.py
packagelister/py.typed
packagelister/whouses.py
packagelister-2.2.0.dist-info/METADATA
packagelister-2.2.0.dist-info/WHEEL
packagelister-2.2.0.dist-info/entry_points.txt
packagelister-2.2.0.dist-info/licenses/LICENSE.txt
packagelister-2.2.0.dist-info/RECORD
