Metadata-Version: 2.4
Name: packagelister
Version: 2.2.0
Summary: Determine what 3rd-party packages a project imports.
Project-URL: Homepage, https://github.com/matt-manes/packagelister
Project-URL: Documentation, https://github.com/matt-manes/packagelister/tree/main/docs
Project-URL: Source code, https://github.com/matt-manes/packagelister/tree/main/src/packagelister
Author: Matt Manes
License-File: LICENSE.txt
Keywords: import,module,package
Classifier: License :: OSI Approved :: MIT License
Classifier: Operating System :: OS Independent
Classifier: Programming Language :: Python :: 3
Requires-Python: >=3.10
Requires-Dist: argshell
Requires-Dist: pathier>=1.3.4
Requires-Dist: printbuddies>=1.4.1
Requires-Dist: rich
Requires-Dist: typing-extensions>=4.7.1
Requires-Dist: younotyou
